{"cameraMode":{"drawMode":0,"name":"Shaded","section":"Shading Mode"},"sceneLighting":false,"audioPlay":false,"sceneViewState":{"m_AlwaysRefresh":false,"showFog":true,"showSkybox":false,"showFlares":true,"showImageEffects":true,"showParticleSystems":true,"showVisualEffectGraphs":true,"m_FxEnabled":true},"in2DMode":false,"pivot":{"x":-2.499999761581421,"y":1.9999998807907105,"z":-2.4243075847625734},"rotation":{"x":-0.1446717530488968,"y":-0.8458212018013,"z":0.28773045539855959,"w":-0.4252830445766449},"size":9.114651679992676,"orthographic":false}